masked_prosody_model/__init__.py
masked_prosody_model/measures.py
masked_prosody_model/modules.py
masked_prosody_model-0.3.0.dist-info/METADATA
masked_prosody_model-0.3.0.dist-info/WHEEL
masked_prosody_model-0.3.0.dist-info/RECORD
