Metadata-Version: 2.3
Name: masked_prosody_model
Version: 0.3.0
Author-email: Christoph Minixhofer <christoph.minixhofer@gmail.com>
License: MIT
Requires-Python: >=3.8
Requires-Dist: librosa>=0.9.2
Requires-Dist: nnaudio==0.3.1
Requires-Dist: numpy<2
Requires-Dist: pandas>=2.0.3
Requires-Dist: pyworld-prebuilt>=0.3.2
Requires-Dist: pyyaml>=6.0.1
Requires-Dist: rich>=13.6.0
Requires-Dist: transformers>=4.34.0
Provides-Extra: test
Requires-Dist: pytest-cov>=4.0.0; extra == 'test'
Requires-Dist: pytest>=7.0.0; extra == 'test'
